crams/__init__.py
crams/admin.py
crams/apps.py
crams/models.py
crams/permissions.py
crams/test_utils.py
crams/user_manager.py
crams/constants/__init__.py
crams/constants/api.py
crams/constants/code.py
crams/constants/db.py
crams/extension/__init__.py
crams/extension/config_init.py
crams/extension/crams_aspects.py
crams/extension/tests.py
crams/migrations/0001_auth.py
crams/migrations/0002_erb.py
crams/migrations/0003_lookup.py
crams/migrations/0004_provider.py
crams/migrations/0005_support.py
crams/migrations/0006_cramstoken.py
crams/migrations/0007_costunittype_zone.py
crams/migrations/0008_load_crams_lookups.py
crams/migrations/0009_projectmemberstatus.py
crams/migrations/0010_projectmemberstatus_lookups.py
crams/migrations/0011_softwarelicensestatus.py
crams/migrations/__init__.py
crams/serializers/__init__.py
crams/serializers/erb_serializers.py
crams/serializers/lookup_serializers.py
crams/serializers/model_serializers.py
crams/serializers/provision_details_serializer.py
crams/serializers/question_serializers.py
crams/serializers/utilitySerializers.py
crams/sqls/__init__.py
crams/sqls/for_code.sql
crams/sqls/project_duration.sql
crams/sqls/project_member_status.sql
crams/sqls/seo_code.sql
crams/sqls/software_status.sql
crams/templates/__init__.py
crams/templates/swagger-ui.html
crams/templates/registration/login.html
crams/utils/__init__.py
crams/utils/action_state.py
crams/utils/crams_utils.py
crams/utils/date_utils.py
crams/utils/debug.py
crams/utils/django_utils.py
crams/utils/lang_utils.py
crams/utils/model_lookup_utils.py
crams/utils/param_utils.py
crams/utils/provision_detail_utils.py
crams/utils/rest_utils.py
crams/utils/role.py
crams/utils/user_utils.py
crams/utils/validaton_utils.py
crams/utils/viewset_utils.py
crams/views/__init__.py
crams/views/auth.py
crams/views/funding_body.py
crams/views/lookup_api.py
merc_common/__init__.py
merc_common/asgi.py
merc_common/settings.py
merc_common/test_settings.py
merc_common/urls.py
merc_common/wsgi.py
merc_common-1.0.2.7.dist-info/METADATA
merc_common-1.0.2.7.dist-info/WHEEL
merc_common-1.0.2.7.dist-info/top_level.txt
merc_common-1.0.2.7.dist-info/RECORD
